spade_cli.py
spade_rescue.py
spade_client/ApplicationFunction.py
spade_client/BundlesFunction.py
spade_client/Display.py
spade_client/ItemsFunction.py
spade_client/Spade.py
spade_client/TicketsFunction.py
spade_client/TimingFunction.py
spade_client/__init__.py
spade_client-5.2.0.dist-info/LICENSE.txt
spade_client-5.2.0.dist-info/METADATA
spade_client-5.2.0.dist-info/WHEEL
spade_client-5.2.0.dist-info/entry_points.txt
spade_client-5.2.0.dist-info/top_level.txt
spade_client-5.2.0.dist-info/RECORD
