Metadata-Version: 2.1
Name: spade-client
Version: 5.2.0
Summary: Manage the connection and communications to a Spade server.
Home-page: http://nest.lbl.gov/projects/spade
Author: Simon Patton
Author-email: sjpatton@lbl.gov
Classifier: Development Status :: 5 - Production/Stable
Classifier: Intended Audience :: Developers
Classifier: Topic :: Scientific/Engineering
Classifier: License :: OSI Approved :: BSD License
Classifier: Programming Language :: Python :: 2.7
Classifier: Programming Language :: Python :: 3
Classifier: Programming Language :: Python :: 3.4
Classifier: Programming Language :: Python :: 3.5
Classifier: Programming Language :: Python :: 3.6
Classifier: Programming Language :: Python :: 3.7
Requires-Python: >=2.7, !=3.0.*, !=3.1.*, !=3.2.*, !=3.3.*, <4
License-File: LICENSE.txt
Requires-Dist: requests
